<?xml version="1.0" encoding="gb2312"?>
<?xml-stylesheet type="text/xsl" href="family.xsl"?>
<!--xml与xsl结合就可以转换成html显示，不需要schema。如果要引入schema，xml根结点中的namespace必须与xsl中一致。不要设默认namespace。
<Family xmlns="http://www.bansi.com/schemas/family" xmlns:xsi="http://www.w3.org/2001/XMLSchema-instance" xsi:schemaLocation="http://www.bansi.com/schemas/family family.xsd" xsi:noNamespaceSchemaLocation="family.xsd">
-->
<a:FamilySet xmlns:a="http://www.bansi.com/schemas/family" xmlns:xsi="http://www.w3.org/2001/XMLSchema-instance" xsi:schemaLocation="http://www.bansi.com/schemas/family family.xsd" xsi:noNamespaceSchemaLocation="family.xsd">
	<Family>
		<FamilyName>LiQian's Family</FamilyName>
		<FamilyMember>
			<Name>LiQian</Name>
			<Birthday>2016-10-20</Birthday>
			<Gender>男</Gender>
			<Address>
				<Contury>中国</Contury>
				<Province>福建</Province>
				<City>厦门</City>
			</Address>
			<Role>Son</Role>
			<Age>2</Age>
		</FamilyMember>
		<FamilyMember>
			<Name>Bansi</Name>
			<Birthday>1988-12-10</Birthday>
			<Gender>男</Gender>
			<Address>
				<Contury>中国</Contury>
				<Province>湖北</Province>
				<City>通城</City>
				<Address1>朱家坡</Address1>
			</Address>
			<Role>Father</Role>
			<Age>30</Age>
		</FamilyMember>
	</Family>
	<Family>
		<FamilyName>XiaoJie's Family</FamilyName>
		<FamilyMember>
			<Name>XiaoJie</Name>
			<Birthday>2010-09-14</Birthday>
			<Gender>男</Gender>
			<Address>
				<Contury>中国</Contury>
				<Province>湖北</Province>
				<City>武汉</City>
			</Address>
			<Role>Son</Role>
			<Age>8</Age>
		</FamilyMember>
		<FamilyMember>
			<Name>Wind</Name>
			<Birthday>1982-04-06</Birthday>
			<Gender>女</Gender>
			<Address>
				<Contury>中国</Contury>
				<Province>湖北</Province>
				<City>通城</City>
				<Address1>朱家坡</Address1>
			</Address>
			<Role>Mother</Role>
			<Age>36</Age>
		</FamilyMember>
	</Family>
</a:FamilySet>
